filewise/__init__.py
filewise-3.11.10.dist-info/licenses/LICENSE
filewise-3.11.10.dist-info/METADATA
filewise-3.11.10.dist-info/WHEEL
filewise-3.11.10.dist-info/top_level.txt
filewise-3.11.10.dist-info/RECORD
