Metadata-Version: 2.4
Name: filewise
Version: 3.11.10
Summary: A Python package for efficient file and directory management, featuring tools for bulk renaming, data handling, and format conversion
Author-email: Jon Ander Gabantxo <jagabantxo@gmail.com>
License: MIT License
Project-URL: Homepage, https://github.com/EusDancerDev/filewise
Project-URL: Documentation, https://github.com/EusDancerDev/filewise#readme
Project-URL: Repository, https://github.com/EusDancerDev/filewise.git
Project-URL: Bug Reports, https://github.com/EusDancerDev/filewise/issues
Keywords: file management,directory operations,bulk renaming,data handling,format conversion
Classifier: Development Status :: 4 - Beta
Classifier: Intended Audience :: Developers
Classifier: Programming Language :: Python :: 3
Classifier: Programming Language :: Python :: 3.10
Classifier: Programming Language :: Python :: 3.11
Classifier: Programming Language :: Python :: 3.12
Classifier: Operating System :: OS Independent
Classifier: Topic :: Software Development :: Libraries :: Python Modules
Classifier: Topic :: Utilities
Requires-Python: >=3.10
License-File: LICENSE
Requires-Dist: pandas>=1.3.0
Requires-Dist: xarray>=2024.2.0
Requires-Dist: numpy>=1.21.0
Requires-Dist: pygenutils>=16.3.0
Requires-Dist: paramlib>=3.4.10
Provides-Extra: dev
Requires-Dist: pytest>=7.0.0; extra == "dev"
Requires-Dist: pytest-cov>=4.0.0; extra == "dev"
Requires-Dist: black>=22.0.0; extra == "dev"
Requires-Dist: flake8>=5.0.0; extra == "dev"
Dynamic: license-file
